{
  "styles": [
    { "name": "Bigroom", "icon": "🎵", "description": "Massive festival sounds" },
    { "name": "Afro House", "icon": "🌍", "description": "Rhythmic African beats" },
    { "name": "Amapiano", "icon": "🎹", "description": "South African piano house" },
    { "name": "Baile Funk", "icon": "🔥", "description": "Brazilian funk energy" },
    { "name": "Commercial EDM", "icon": "⚡", "description": "Mainstream electronic" },
    { "name": "Indobounce", "icon": "🇮🇩", "description": "Indonesian bounce music" },
    { "name": "Open Format", "icon": "🔄", "description": "Versatile genre mixing" },
    { "name": "Live Saxophone", "icon": "🎷", "description": "Live saxophone performance" }
  ]
}